mwparserfromhell-0.7.2.dist-info/RECORD
mwparserfromhell-0.7.2.dist-info/WHEEL
mwparserfromhell-0.7.2.dist-info/top_level.txt
mwparserfromhell-0.7.2.dist-info/METADATA
mwparserfromhell-0.7.2.dist-info/licenses/LICENSE
mwparserfromhell/definitions.py
mwparserfromhell/string_mixin.py
mwparserfromhell/__init__.py
mwparserfromhell/wikicode.py
mwparserfromhell/utils.py
mwparserfromhell/py.typed
mwparserfromhell/smart_list/smart_list.py
mwparserfromhell/smart_list/__init__.py
mwparserfromhell/smart_list/list_proxy.py
mwparserfromhell/smart_list/utils.py
mwparserfromhell/nodes/argument.py
mwparserfromhell/nodes/_base.py
mwparserfromhell/nodes/wikilink.py
mwparserfromhell/nodes/html_entity.py
mwparserfromhell/nodes/comment.py
mwparserfromhell/nodes/__init__.py
mwparserfromhell/nodes/heading.py
mwparserfromhell/nodes/text.py
mwparserfromhell/nodes/template.py
mwparserfromhell/nodes/tag.py
mwparserfromhell/nodes/external_link.py
mwparserfromhell/nodes/extras/attribute.py
mwparserfromhell/nodes/extras/__init__.py
mwparserfromhell/nodes/extras/parameter.py
mwparserfromhell/parser/_tokenizer.cpython-39-darwin.so
mwparserfromhell/parser/__init__.py
mwparserfromhell/parser/tokens.py
mwparserfromhell/parser/builder.py
mwparserfromhell/parser/tokenizer.py
mwparserfromhell/parser/errors.py
mwparserfromhell/parser/contexts.py
mwparserfromhell/parser/ctokenizer/tok_support.h
mwparserfromhell/parser/ctokenizer/tok_parse.c
mwparserfromhell/parser/ctokenizer/textbuffer.h
mwparserfromhell/parser/ctokenizer/tag_data.h
mwparserfromhell/parser/ctokenizer/tokens.h
mwparserfromhell/parser/ctokenizer/tokenizer.h
mwparserfromhell/parser/ctokenizer/avl_tree.c
mwparserfromhell/parser/ctokenizer/definitions.c
mwparserfromhell/parser/ctokenizer/common.h
mwparserfromhell/parser/ctokenizer/tok_parse.h
mwparserfromhell/parser/ctokenizer/tok_support.c
mwparserfromhell/parser/ctokenizer/tag_data.c
mwparserfromhell/parser/ctokenizer/textbuffer.c
mwparserfromhell/parser/ctokenizer/contexts.h
mwparserfromhell/parser/ctokenizer/definitions.h
mwparserfromhell/parser/ctokenizer/tokenizer.c
mwparserfromhell/parser/ctokenizer/tokens.c
