Metadata-Version: 2.4
Name: mwparserfromhell
Version: 0.7.2
Summary: MWParserFromHell is a parser for MediaWiki wikicode
Author-email: Ben Kurtovic <ben@benkurtovic.com>
License-Expression: MIT
Project-URL: Repository, https://github.com/earwig/mwparserfromhell
Project-URL: Documentation, https://mwparserfromhell.readthedocs.io/
Project-URL: Issues, https://github.com/earwig/mwparserfromhell/issues
Project-URL: Changelog, https://github.com/earwig/mwparserfromhell/blob/main/CHANGELOG
Keywords: mwparserfromhell,wikipedia,wiki,mediawiki,wikicode,wikitext
Classifier: Development Status :: 4 - Beta
Classifier: Environment :: Console
Classifier: Intended Audience :: Developers
Classifier: Operating System :: OS Independent
Classifier: Programming Language :: Python :: 3
Classifier: Programming Language :: Python :: 3.9
Classifier: Programming Language :: Python :: 3.10
Classifier: Programming Language :: Python :: 3.11
Classifier: Programming Language :: Python :: 3.12
Classifier: Programming Language :: Python :: 3.13
Classifier: Topic :: Text Processing :: Markup
Requires-Python: >=3.9
License-File: LICENSE
Dynamic: license-file
